wtw_inference_server/__init__.py
wtwco_radar_live_python-2.0.0.dist-info/licenses/LICENCE
wtwco_radar_live_python-2.0.0.dist-info/METADATA
wtwco_radar_live_python-2.0.0.dist-info/WHEEL
wtwco_radar_live_python-2.0.0.dist-info/RECORD
