Metadata-Version: 2.4
Name: wtwco-radar-live-python
Version: 2.0.0
Summary: Radar Live Python inference dependencies.
License: See LICENCE file
License-File: LICENCE
Author: WTW PyPI RLP
Author-email: WTW-PyPI-RLP@wtwco.com
Requires-Python: >=3.9,<3.13
Classifier: License :: Other/Proprietary License
Classifier: Programming Language :: Python :: 3
Classifier: Programming Language :: Python :: 3.9
Classifier: Programming Language :: Python :: 3.10
Classifier: Programming Language :: Python :: 3.11
Classifier: Programming Language :: Python :: 3.12
Requires-Dist: azure-ai-ml (>=1.31.0,<1.32.0)
Requires-Dist: azureml-ai-monitoring (>=1.0,<1.1)
Requires-Dist: azureml-inference-server-http (>=1.5.0,<1.6.0)
